odoo/addons/shopinvader_sale_order_line_delivery_state/README.rst
odoo/addons/shopinvader_sale_order_line_delivery_state/__init__.py
odoo/addons/shopinvader_sale_order_line_delivery_state/__manifest__.py
odoo/addons/shopinvader_sale_order_line_delivery_state/hooks.py
odoo/addons/shopinvader_sale_order_line_delivery_state/i18n/shopinvader_sale_order_line_delivery_state.pot
odoo/addons/shopinvader_sale_order_line_delivery_state/models/__init__.py
odoo/addons/shopinvader_sale_order_line_delivery_state/models/sale_order_line.py
odoo/addons/shopinvader_sale_order_line_delivery_state/readme/CONTRIBUTORS.rst
odoo/addons/shopinvader_sale_order_line_delivery_state/readme/DESCRIPTION.rst
odoo/addons/shopinvader_sale_order_line_delivery_state/services/__init__.py
odoo/addons/shopinvader_sale_order_line_delivery_state/services/abstract_sale.py
odoo/addons/shopinvader_sale_order_line_delivery_state/static/description/index.html
odoo/addons/shopinvader_sale_order_line_delivery_state/tests/__init__.py
odoo/addons/shopinvader_sale_order_line_delivery_state/tests/test_sale.py
odoo13_addon_shopinvader_sale_order_line_delivery_state-13.0.1.0.1.dist-info/METADATA
odoo13_addon_shopinvader_sale_order_line_delivery_state-13.0.1.0.1.dist-info/WHEEL
odoo13_addon_shopinvader_sale_order_line_delivery_state-13.0.1.0.1.dist-info/top_level.txt
odoo13_addon_shopinvader_sale_order_line_delivery_state-13.0.1.0.1.dist-info/RECORD
