Metadata-Version: 2.1
Name: odoo13-addon-shopinvader-sale-order-line-delivery-state
Version: 13.0.1.0.1
Summary: Shopinvader Sale Order Line Delivery State
Home-page: https://github.com/shopinvader/odoo-shopinvader
Author: ForgeFlow
License: AGPL-3
Platform: UNKNOWN
Classifier: Programming Language :: Python
Classifier: Framework :: Odoo
Classifier: License :: OSI Approved :: GNU Affero General Public License v3
Requires-Python: >=3.5
Requires-Dist: odoo13-addon-sale-order-line-delivery-state
Requires-Dist: odoo13-addon-shopinvader
Requires-Dist: odoo (<13.1dev,>=13.0a)
